lpulive/__init__.py
lpulive/__main__.py
lpulive/lpulive_main.py
lpulive/lpulive_urls.py
lpulive-0.3.0.dist-info/LICENCE
lpulive-0.3.0.dist-info/METADATA
lpulive-0.3.0.dist-info/WHEEL
lpulive-0.3.0.dist-info/top_level.txt
lpulive-0.3.0.dist-info/RECORD
