Metadata-Version: 2.1
Name: lpulive
Version: 0.3.0
Summary: Lpulive api for searching, getting messages, getting user detail etc
Home-page: https://github.com/knight-byte/lpulive
Download-URL: https://github.com/knight-byte/lpulive/archive/v0.3.0.tar.gz
Author: Abunachar Yeahhia
Author-email: abunachar1236@gmail.com
License: MIT
Keywords: lpulive search,lpulive api,lpulive,messaging,lpu
Classifier: Intended Audience :: Developers
Classifier: License :: OSI Approved :: MIT License
Classifier: Programming Language :: Python :: 3
License-File: LICENCE
Requires-Dist: bs4
Requires-Dist: requests
Requires-Dist: lxml
